<?xml version="1.0" encoding="UTF-8"?>
<TextureAtlas imagePath="spritesheet.png">
	<SubTexture name="FUCKERS Dancing Beat0000" x="5" y="5" width="132" height="90" frameX="-10" frameY="-17" frameWidth="162" frameHeight="114" />
	<SubTexture name="FUCKERS Dancing Beat0001" x="5" y="5" width="132" height="90" frameX="-10" frameY="-17" frameWidth="162" frameHeight="114" />
	<SubTexture name="FUCKERS Dancing Beat0002" x="157" y="5" width="132" height="90" frameX="-10" frameY="-17" frameWidth="162" frameHeight="114" />
	<SubTexture name="FUCKERS Dancing Beat0003" x="309" y="5" width="132" height="90" frameX="-10" frameY="-17" frameWidth="162" frameHeight="114" />
	<SubTexture name="FUCKERS Dancing Beat0004" x="461" y="5" width="132" height="90" frameX="-10" frameY="-17" frameWidth="162" frameHeight="114" />
	<SubTexture name="FUCKERS Dancing Beat0005" x="461" y="5" width="132" height="90" frameX="-10" frameY="-17" frameWidth="162" frameHeight="114" />
	<SubTexture name="FUCKERS Dancing Beat0006" x="613" y="5" width="132" height="90" frameX="-10" frameY="-17" frameWidth="162" frameHeight="114" />
	<SubTexture name="FUCKERS Dancing Beat0007" x="5" y="115" width="132" height="90" frameX="-10" frameY="-17" frameWidth="162" frameHeight="114" />
	<SubTexture name="FUCKERS Dancing Beat0008" x="157" y="115" width="132" height="90" frameX="-10" frameY="-17" frameWidth="162" frameHeight="114" />
	<SubTexture name="FUCKERS Dancing Beat0009" x="157" y="115" width="132" height="90" frameX="-10" frameY="-17" frameWidth="162" frameHeight="114" />
	<SubTexture name="FUCKERS Dancing Beat0010" x="309" y="115" width="132" height="90" frameX="-10" frameY="-17" frameWidth="162" frameHeight="114" />
	<SubTexture name="FUCKERS Dancing Beat0011" x="461" y="115" width="132" height="90" frameX="-10" frameY="-17" frameWidth="162" frameHeight="114" />
	<SubTexture name="FUCKERS Dancing Beat0012" x="613" y="115" width="132" height="90" frameX="-10" frameY="-17" frameWidth="162" frameHeight="114" />
	<SubTexture name="FUCKERS Dancing Beat0013" x="613" y="115" width="132" height="90" frameX="-10" frameY="-17" frameWidth="162" frameHeight="114" />
	<SubTexture name="FUCKERS Dancing Beat0014" x="613" y="115" width="132" height="90" frameX="-10" frameY="-17" frameWidth="162" frameHeight="114" />
	<SubTexture name="FUCKERS Dancing Beat0015" x="5" y="225" width="132" height="90" frameX="-10" frameY="-17" frameWidth="162" frameHeight="114" />
	<SubTexture name="FUCKERS Dancing Beat0016" x="5" y="225" width="132" height="90" frameX="-10" frameY="-17" frameWidth="162" frameHeight="114" />
	<SubTexture name="FUCKERS Dancing Beat0017" x="157" y="225" width="132" height="90" frameX="-10" frameY="-17" frameWidth="162" frameHeight="114" />
	<SubTexture name="FUCKERS Dancing Beat0018" x="309" y="225" width="132" height="90" frameX="-10" frameY="-17" frameWidth="162" frameHeight="114" />
	<SubTexture name="FUCKERS Dancing Beat0019" x="461" y="225" width="132" height="90" frameX="-10" frameY="-17" frameWidth="162" frameHeight="114" />
	<SubTexture name="FUCKERS Dancing Beat0020" x="613" y="225" width="132" height="90" frameX="-10" frameY="-17" frameWidth="162" frameHeight="114" />
	<SubTexture name="FUCKERS Dancing Beat0021" x="5" y="335" width="132" height="90" frameX="-10" frameY="-17" frameWidth="162" frameHeight="114" />
	<SubTexture name="FUCKERS Dancing Beat0022" x="157" y="335" width="132" height="90" frameX="-10" frameY="-17" frameWidth="162" frameHeight="114" />
	<SubTexture name="FUCKERS Dancing Beat0023" x="309" y="335" width="132" height="90" frameX="-10" frameY="-17" frameWidth="162" frameHeight="114" />
	<SubTexture name="FUCKERS Dancing Beat0024" x="309" y="335" width="132" height="90" frameX="-10" frameY="-17" frameWidth="162" frameHeight="114" />
	<SubTexture name="FUCKERS Dancing Beat0025" x="461" y="335" width="132" height="90" frameX="-10" frameY="-17" frameWidth="162" frameHeight="114" />
	<SubTexture name="FUCKERS Dancing Beat0026" x="613" y="335" width="132" height="90" frameX="-10" frameY="-17" frameWidth="162" frameHeight="114" />
	<SubTexture name="FUCKERS Dancing Beat0027" x="5" y="455" width="132" height="90" frameX="-10" frameY="-17" frameWidth="162" frameHeight="114" />
	<SubTexture name="FUCKERS Dancing Beat0028" x="5" y="455" width="132" height="90" frameX="-10" frameY="-17" frameWidth="162" frameHeight="114" />
	<SubTexture name="FUCKERS Dancing Beat0029" x="157" y="455" width="132" height="90" frameX="-10" frameY="-17" frameWidth="162" frameHeight="114" />
</TextureAtlas>